Topsis_Kunal_102053007/Kunal_102053007.py
Topsis_Kunal_102053007-0.3.dist-info/METADATA
Topsis_Kunal_102053007-0.3.dist-info/WHEEL
Topsis_Kunal_102053007-0.3.dist-info/entry_points.txt
Topsis_Kunal_102053007-0.3.dist-info/top_level.txt
Topsis_Kunal_102053007-0.3.dist-info/RECORD
