Metadata-Version: 2.1
Name: Topsis-Kunal-102053007
Version: 0.3
Summary: This is a topsis package of version 0.3
Home-page: UNKNOWN
Author: Kunal Madan
Author-email: kmadan_bemba20@thapar.edu
License: UNKNOWN
Platform: UNKNOWN
Requires-Dist: pandas
